examples/__init__.py
examples/isosurf.py
examples/radial_plot.py
hwaves/__init__.py
hwaves/hwf.py
hwaves/hwf_density.py
hwaves/hwf_gui.py
hwaves/hwf_plot.py
hwaves-0.0.2.dist-info/METADATA
hwaves-0.0.2.dist-info/RECORD
hwaves-0.0.2.dist-info/WHEEL
hwaves-0.0.2.dist-info/top_level.txt
tests/__init__.py
tests/test_hwf_density.py
tests/test_hwf_plots.py
