Metadata-Version: 2.1
Name: hwaves
Version: 0.0.2
Summary: Compute and plot hydrogenic wavefunctions
Home-page: https://github.com/lensonp/hwaves.git
Author: Lenson A. Pellouchoud
Author-email: UNKNOWN
License: BSD
Platform: UNKNOWN
Requires-Dist: numpy
Requires-Dist: scipy
Requires-Dist: masstable
Requires-Dist: periodictable
